http_file_streamer/__init__.py
http_file_streamer/receiver.py
http_file_streamer/streamer.py
http_file_streamer-0.1.3.dist-info/LICENSE
http_file_streamer-0.1.3.dist-info/METADATA
http_file_streamer-0.1.3.dist-info/WHEEL
http_file_streamer-0.1.3.dist-info/top_level.txt
http_file_streamer-0.1.3.dist-info/RECORD
