Metadata-Version: 2.1
Name: http_file_streamer
Version: 0.1.3
Summary: A package for streaming and receiving files.
Home-page: https://github.com/babakzarrinbal/httpfilestreamer.git
Author: Babak Zarrinbal
Author-email: babak.zarrinbal@gmail.com
Classifier: Programming Language :: Python :: 3
Classifier: License :: OSI Approved :: MIT License
Classifier: Operating System :: OS Independent
Requires-Python: >=3.6
License-File: LICENSE
Requires-Dist: requests
